{
  "$schema": "https://schema.management.azure.com/schemas/2019-04-01/deploymentTemplate.json#",
  "contentVersion": "1.0.0.0",
  "parameters": {
    "subscriptionId": {
      "type": "string"
    },
    "name": {
      "type": "string",
      "defaultValue": "webApp1",
      "metadata": {
        "description": "Web App name that will be prefixed to .azurewebsites.net"
      }
    },
    "serverFarmResourceGroup": {
      "type": "string"
    },
    "hostingPlanName": {
      "type": "string"
    }
  },
  "functions": [],
  "variables": {},
  "resources": [
    {
      "name": "[parameters('name')]",
      "type": "Microsoft.Web/sites",
      "apiVersion": "2018-11-01",
      "location": "[resourceGroup().location]",
      "tags": {
        "[concat('hidden-related:', resourceGroup().id, '/providers/Microsoft.Web/serverfarms/appServicePlan1')]": "Resource",
        "displayName": "[parameters('name')]"
      },
      "dependsOn": [
        "[resourceId('Microsoft.Web/serverfarms', 'appServicePlan1')]"
      ],
      "properties": {
        "name": "[parameters('name')]",
        "serverFarmId": "[concat('/subscriptions/', parameters('subscriptionId'),'/resourcegroups/', parameters('serverFarmResourceGroup'), '/providers/Microsoft.Web/serverfarms/', parameters('hostingPlanName'))]",
        "siteConfig": {
          "appSettings": [
            {
              "name": "DOCKER_REGISTRY_SERVER_URL",
              "value": "https://index.docker.io"
            },
            {
              "name": "WEBSITES_ENABLE_APP_SERVICE_STORAGE",
              "value": "true"
            }
          ],
          "linuxFxVersion": "DOCKER|ionutcarp/node-red-docker-az-web-app:latest"
        }
      }
    }
  ],
  "outputs": {}
}